setup.py
PyFinFeed.egg-info/PKG-INFO
PyFinFeed.egg-info/SOURCES.txt
PyFinFeed.egg-info/dependency_links.txt
PyFinFeed.egg-info/requires.txt
PyFinFeed.egg-info/top_level.txt
finfeed/__init__.py
finfeed/client.py
finfeed/utils.py
finfeed/auth/__init__.py
finfeed/auth/base.py
finfeed/auth/client_credentials.py